{
  "services": [
    {
      "title": "Ατομικές Συνεδρίες",
      "description": "Προσωπικός χώρος δημιουργικής έκφρασης και θεραπευτικής διερεύνησης. Κάθε συνεδρία σχεδιάζεται με βάση τις μοναδικές ανάγκες σας.",
      "idealFor": [
        "Ενήλικες που αναζητούν αυτογνωσία, διαχείριση συναισθημάτων ή αντιμετώπιση συγκεκριμένων δυσκολιών."
      ],
      "format": "Δια ζώσης ή διαδικτυακά",
      "duration": "50 λεπτά ανά συνεδρία",
      "whatToExpect": [
        "Στην πρώτη συνάντηση γνωριζόμαστε και διαμορφώνουμε μαζί τους στόχους.",
        "Κάθε συνεδρία περιλαμβάνει δημιουργική δραστηριότητα και αναστοχασμό."
      ]
    },
    {
      "title": "Ομαδικές Συνεδρίες",
      "description": "Μικρές θεραπευτικές ομάδες που συνδυάζουν τη δύναμη της ομάδας με τη δημιουργική έκφραση. Ένα πλαίσιο σύνδεσης και αλληλοϋποστήριξης.",
      "idealFor": [
        "Ενήλικες που επιθυμούν ομαδική εμπειρία, κοινή διερεύνηση και σύνδεση με άλλους."
      ],
      "format": "Δια ζώσης",
      "duration": "90 λεπτά ανά συνεδρία",
      "whatToExpect": [
        "Οι ομάδες λειτουργούν σε κλειστό πλαίσιο με σταθερά μέλη.",
        "Κάθε συνάντηση περιλαμβάνει θεματική δημιουργική δραστηριότητα και ομαδικό αναστοχασμό."
      ]
    }
  ]
}
